<!--Verisurf Server Welcome Message-->
<response><success><command_received>inspect_plan_list</command_received><data><plans><plan id="0">Plan1</plan></plans></data><completed /><request_id>0</request_id></success></response><response><success><command_received>inspect_plan_load</command_received><request_id>1</request_id></success></response><response><success><command_received>inspect_plan_info</command_received><data><inspect_plan_info><plan id="0" run_state="0">Plan1<plan_object object_id="0">Ellipse1</plan_object><plan_object object_id="1">Plane1</plan_object></plan></inspect_plan_info></data><completed /><request_id>2</request_id></success></response><response><success><command_received>measure_get_point_mode</command_received><data>2</data><completed /><request_id>5</request_id></success></response><response><success><command_received>object_list</command_received><data><object_info><object id="0" type="Plan">Plan1</object><object id="1" type="Ellipse" group="Feature">Ellipse1</object></object_info></data><completed /><request_id>11</request_id></success></response>